oni_interpreter.py
oni_interpreter-0.1.0.dist-info/METADATA
oni_interpreter-0.1.0.dist-info/WHEEL
oni_interpreter-0.1.0.dist-info/entry_points.txt
oni_interpreter-0.1.0.dist-info/top_level.txt
oni_interpreter-0.1.0.dist-info/RECORD
