Metadata-Version: 2.4
Name: oni-interpreter
Version: 0.1.0
Summary: Interpretador da linguagem Oni/Uni
Author: Arthur Fillipy
Author-email: arthurfillipy20@gmail.com
Classifier: Programming Language :: Python :: 3
Classifier: License :: OSI Approved :: MIT License
Classifier: Operating System :: OS Independent
Requires-Python: >=3.6
Dynamic: author
Dynamic: author-email
Dynamic: classifier
Dynamic: requires-python
Dynamic: summary
